korean_number/__init__.py
korean_number/addunit.py
korean_number/kor2num.py
korean_number/kor_constants.py
korean_number/kor_utils.py
korean_number/num2finkor.py
korean_number/num2kor.py
korean_number/split_by_4.py
korean_number-1.0.2.dist-info/licenses/LICENSE
korean_number-1.0.2.dist-info/METADATA
korean_number-1.0.2.dist-info/WHEEL
korean_number-1.0.2.dist-info/top_level.txt
korean_number-1.0.2.dist-info/RECORD
