Metadata-Version: 2.4
Name: korean_number
Version: 1.0.2
Summary: 숫자와 한글 숫자 변환 파이썬 패키지
Author-email: yegang hwang <yegang@yegangs.com>
License: MIT License
Requires-Python: >=3.7
License-File: LICENSE
Dynamic: license-file
